htmltestrunner/__init__.py
htmltestrunner/runner.py
htmltestrunner_modern-1.0.1.dist-info/LICENSE
htmltestrunner_modern-1.0.1.dist-info/METADATA
htmltestrunner_modern-1.0.1.dist-info/WHEEL
htmltestrunner_modern-1.0.1.dist-info/top_level.txt
htmltestrunner_modern-1.0.1.dist-info/RECORD
