Metadata-Version: 2.1
Name: htmltestrunner-modern
Version: 1.0.1
Summary: 现代化的 Python unittest HTML 测试报告生成器
Home-page: https://github.com/Aquarius-0455/HTMLTestRunner-Modern
Author: Lit
Author-email: Lit <clm24Kmagic@163.com>
License: MIT
Project-URL: Homepage, https://github.com/Aquarius-0455/HTMLTestRunner-Modern
Project-URL: Repository, https://github.com/Aquarius-0455/HTMLTestRunner-Modern
Project-URL: Issues, https://github.com/Aquarius-0455/HTMLTestRunner-Modern/issues
Keywords: unittest,test,testing,report,html,htmltestrunner
Classifier: Development Status :: 5 - Production/Stable
Classifier: Intended Audience :: Developers
Classifier: Topic :: Software Development :: Testing
Classifier: License :: OSI Approved :: MIT License
Classifier: Programming Language :: Python :: 3
Classifier: Programming Language :: Python :: 3.7
Classifier: Programming Language :: Python :: 3.8
Classifier: Programming Language :: Python :: 3.9
Classifier: Programming Language :: Python :: 3.10
Classifier: Programming Language :: Python :: 3.11
Classifier: Programming Language :: Python :: 3.12
Classifier: Operating System :: OS Independent
Requires-Python: >=3.7
License-File: LICENSE
